productanalyzer/__init__.py
productanalyzer/indicators.py
productanalyzer/manager.py
productanalyzer/object.py
productanalyzer/product.py
productanalyzer/score.py
productanalyzer/util.py
productanalyzer-0.1.1.dist-info/METADATA
productanalyzer-0.1.1.dist-info/WHEEL
productanalyzer-0.1.1.dist-info/RECORD
