Metadata-Version: 2.1
Name: productanalyzer
Version: 0.1.1
Summary: 计算产品各项风险收益指标
License: MIT
Author: xuanqi
Requires-Python: >=3.8,<4.0
Classifier: License :: OSI Approved :: MIT License
Classifier: Programming Language :: Python :: 3
Classifier: Programming Language :: Python :: 3.8
Classifier: Programming Language :: Python :: 3.9
Classifier: Programming Language :: Python :: 3.10
Classifier: Programming Language :: Python :: 3.11
Requires-Dist: openpyxl (>=3.1.2,<4.0.0)
Requires-Dist: pandas (>=1.4,<2.0)
Requires-Dist: statsmodels (>=0.14.0,<0.15.0)
